cardamom/__init__.py
cardamom/inference/__init__.py
cardamom/inference/kinetics.py
cardamom/inference/network.py
cardamom/model/__init__.py
cardamom/model/base.py
cardamom-0.0.3.dist-info/METADATA
cardamom-0.0.3.dist-info/WHEEL
cardamom-0.0.3.dist-info/licenses/LICENSE.txt
cardamom-0.0.3.dist-info/RECORD
