Metadata-Version: 2.4
Name: cardamom
Version: 0.0.3
Summary: A package for inference and simulation of gene regulatory networks
Project-URL: Homepage, https://github.com/eliasventre/cardamom
Author-email: Elias Ventre <elias.ventre@inria.fr>, Ulysse Herbach <ulysse.herbach@inria.fr>
License-File: LICENSE.txt
Classifier: License :: OSI Approved :: BSD License
Classifier: Operating System :: OS Independent
Classifier: Programming Language :: Python :: 3
Requires-Python: >=3.10
Requires-Dist: alive-progress
Requires-Dist: harissa
Requires-Dist: matplotlib>=3.8
Requires-Dist: numba>=0.60
Requires-Dist: numpy>=1.26
Requires-Dist: scipy>=1.13
Requires-Dist: umap-learn
